LICENSE
scikeras/__init__.py
scikeras/_saving_utils.py
scikeras/_utils.py
scikeras/utils/__init__.py
scikeras/utils/random_state.py
scikeras/utils/transformers.py
scikeras/wrappers.py
scikeras-0.9.0.dist-info/LICENSE
scikeras-0.9.0.dist-info/WHEEL
scikeras-0.9.0.dist-info/METADATA
scikeras-0.9.0.dist-info/RECORD
