Metadata-Version: 2.1
Name: scikeras
Version: 0.9.0
Summary: Scikit-Learn API wrapper for Keras.
Home-page: https://github.com/adriangb/scikeras
License: MIT
Keywords: keras,tensorflow,scikit-learn,deep-learning,python
Author: Adrian Garcia Badaracco
Author-email: 1755071+adriangb@users.noreply.github.com
Requires-Python: >=3.7.0,<3.11.0
Classifier: Development Status :: 2 - Pre-Alpha
Classifier: Intended Audience :: Developers
Classifier: Intended Audience :: Education
Classifier: Intended Audience :: Science/Research
Classifier: License :: OSI Approved :: MIT License
Classifier: Natural Language :: English
Classifier: Operating System :: OS Independent
Classifier: Programming Language :: Python :: 3
Classifier: Programming Language :: Python :: 3.10
Classifier: Programming Language :: Python :: 3.7
Classifier: Programming Language :: Python :: 3.8
Classifier: Programming Language :: Python :: 3.9
Classifier: Topic :: Software Development :: Libraries
Classifier: Topic :: Software Development :: Libraries :: Python Modules
Provides-Extra: tensorflow
Provides-Extra: tensorflow-cpu
Requires-Dist: importlib-metadata (>=3); python_version < "3.8"
Requires-Dist: packaging (>=0.21)
Requires-Dist: scikit-learn (>=1.0.0)
Requires-Dist: tensorflow (>=2.7.0); extra == "tensorflow"
Requires-Dist: tensorflow-cpu (>=2.7.0); extra == "tensorflow-cpu"
Project-URL: Documentation, https://www.adriangb.com/scikeras/
Project-URL: Repository, https://github.com/adriangb/scikeras
